Datasetchecker/__init__.py
Datasetchecker/check_for_errors.py
datasetchecker-0.1.0.dist-info/LICENSE.txt
datasetchecker-0.1.0.dist-info/METADATA
datasetchecker-0.1.0.dist-info/WHEEL
datasetchecker-0.1.0.dist-info/top_level.txt
datasetchecker-0.1.0.dist-info/RECORD
