Metadata-Version: 2.1
Name: datasetchecker
Version: 0.1.0
Summary: A library for checking datasets for common errors like missing values, duplicates, data type mismatches, and outliers.
Author: Muhammad Ammar Jamshed
Author-email: ammarjamshed123@gmail.com
Classifier: Programming Language :: Python :: 3
Classifier: License :: OSI Approved :: MIT License
Classifier: Operating System :: OS Independent
Requires-Python: >=3.6
License-File: LICENSE.txt
Requires-Dist: pandas >=1.5.3
